ks_zigpy_espzb-0.0.1.dist-info/licenses/COPYING
ks_zigpy_espzb-0.0.1.dist-info/licenses/LICENSE
zigpy_espzb/__init__.py
zigpy_espzb/api.py
zigpy_espzb/commands.py
zigpy_espzb/exception.py
zigpy_espzb/types.py
zigpy_espzb/uart.py
zigpy_espzb/zigbee/__init__.py
zigpy_espzb/zigbee/application.py
ks_zigpy_espzb-0.0.1.dist-info/METADATA
ks_zigpy_espzb-0.0.1.dist-info/WHEEL
ks_zigpy_espzb-0.0.1.dist-info/top_level.txt
ks_zigpy_espzb-0.0.1.dist-info/RECORD
